Adders/Full/main.v
module full_adder(
    input a,b,c,
    output sum,carry
);
    assign sum=a^b^c;
    assign carry=(a&b)|(b&c)|(c&a);
endmodule

Adders/Full/test.v
module tb_full_adder;

reg a,b,c;
wire sum,carry;

full_adder uut(
    .a(a),.b(b),.c(c),
    .sum(sum),.carry(carry)
);

initial begin
    $dumpfile("full_adder.vcd");
    $dumpvars(0,tb_full_adder);

    a=0;b=0;c=0; #10;
    a=0;b=0;c=1; #10;
    a=0;b=1;c=0; #10;
    a=0;b=1;c=1; #10;
    a=1;b=0;c=0; #10;
    a=1;b=0;c=1; #10;
    a=1;b=1;c=0; #10;
    a=1;b=1;c=1; #10;
    $finish;
end
endmodule

Adders/Full/full_adder.vcd
$date
	Sat Dec 27 07:19:56 2025
$end
$version
	Icarus Verilog
$end
$timescale
	1s
$end
$scope module tb_full_adder $end
$var wire 1 ! sum $end
$var wire 1 " carry $end
$var reg 1 # a $end
$var reg 1 $ b $end
$var reg 1 % c $end
$scope module uut $end
$var wire 1 # a $end
$var wire 1 $ b $end
$var wire 1 % c $end
$var wire 1 " carry $end
$var wire 1 ! sum $end
$upscope $end
$upscope $end
$enddefinitions $end
#0
$dumpvars
0%
0$
0#
0"
0!
$end
#10
1!
1%
#20
0%
1$
#30
1"
0!
1%
#40
0"
1!
0%
0$
1#
#50
1"
0!
1%
#60
0%
1$
#70
1!
1%
